langchain_graphiti/__init__.py
langchain_graphiti/_client.py
langchain_graphiti/_version.py
langchain_graphiti/config.py
langchain_graphiti/exceptions.py
langchain_graphiti/py.typed
langchain_graphiti/retrievers.py
langchain_graphiti/tools.py
langchain_graphiti/utils.py
langchain_graphiti-0.1.1.dist-info/METADATA
langchain_graphiti-0.1.1.dist-info/WHEEL
langchain_graphiti-0.1.1.dist-info/RECORD
