Metadata-Version: 2.3
Name: langchain-graphiti
Version: 0.1.1
Summary: LangChain integration for the Graphiti knowledge graph system.
License: MIT
Keywords: langchain,langgraph,graphiti,knowledge graph,retriever
Author: Mirza Bicer
Author-email: mirzabicer.dev@gmail.com
Requires-Python: >=3.10,<3.14
Classifier: Development Status :: 4 - Beta
Classifier: Intended Audience :: Developers
Classifier: License :: OSI Approved :: MIT License
Classifier: Programming Language :: Python :: 3
Classifier: Programming Language :: Python :: 3.10
Classifier: Programming Language :: Python :: 3.11
Classifier: Programming Language :: Python :: 3.12
Classifier: Programming Language :: Python :: 3.13
Classifier: Topic :: Scientific/Engineering :: Artificial Intelligence
Classifier: Topic :: Software Development :: Libraries :: Python Modules
Provides-Extra: anthropic
Provides-Extra: azure
Provides-Extra: falkordb
Provides-Extra: gemini
Provides-Extra: groq
Provides-Extra: neo4j
Provides-Extra: ollama
Provides-Extra: openai
Requires-Dist: anyio
Requires-Dist: graphiti-core
Requires-Dist: langchain-core
Requires-Dist: langsmith
Requires-Dist: nest-asyncio
Requires-Dist: pydantic (>=2.0,<3.0)
Project-URL: Homepage, https://github.com/dev-mirzabicer/langchain_graphiti
Project-URL: Repository, https://github.com/dev-mirzabicer/langchain_graphiti
